package_test/__init__.py
package_test/linvpy.py
package_test/setup.py
pandiglou-0.1.5492.dist-info/DESCRIPTION.rst
pandiglou-0.1.5492.dist-info/METADATA
pandiglou-0.1.5492.dist-info/RECORD
pandiglou-0.1.5492.dist-info/WHEEL
pandiglou-0.1.5492.dist-info/metadata.json
pandiglou-0.1.5492.dist-info/top_level.txt
