Metadata-Version: 2.0
Name: pandiglou
Version: 0.1.5492
Summary: Package to solve linear inverse problems
Home-page: https://github.com/GuillaumeBeaud/linvpy
Author: Guillaume Beaud, Marta Martinez-Camara
Author-email: beaudguillaume@gmail.com
License: BSD
Keywords: linear inverse M-estimator regression
Platform: UNKNOWN
Classifier: Development Status :: 2 - Pre-Alpha
Classifier: Programming Language :: Python :: 2
Classifier: Programming Language :: Python :: 2.6
Classifier: Programming Language :: Python :: 2.7
Classifier: Programming Language :: Python :: 3
Classifier: Programming Language :: Python :: 3.3
Classifier: Programming Language :: Python :: 3.4
Classifier: Programming Language :: Python :: 3.5
Requires-Dist: numpy
Requires-Dist: scipy
